lean4_lambda_calculator/.DS_Store
lean4_lambda_calculator/__init__.py
lean4_lambda_calculator/analyse_log.py
lean4_lambda_calculator/calculator.py
lean4_lambda_calculator/data_downloader.py
lean4_lambda_calculator/expr.py
lean4_lambda_calculator/level.py
lean4_lambda_calculator/parser.py
lean4_lambda_calculator/shell.py
lean4_lambda_calculator-0.1.1.dist-info/METADATA
lean4_lambda_calculator-0.1.1.dist-info/WHEEL
lean4_lambda_calculator-0.1.1.dist-info/RECORD
